bussim2/__about__.py
bussim2/__init__.py
bussim2/__main__.py
bussim2/bussim.py
bussim2/bussimclasses.py
bussim2/minbus.py
bussim2/utilities.py
bussim2/sources/blocks.db
bussim2/sources/buffer_times.csv
bussim2/sources/bus_battery_sizes.csv
bussim2/sources/classless.css
bussim2/sources/config.ini
bussim2/sources/demand_rates.csv
bussim2/sources/depot_info.csv
bussim2/sources/energy_rates.csv
bussim2/sources/nyc_temps.json
bussim2/sources/service_calendar.csv
bussim2/sources/service_calendar_simplified.csv
bussim2/sources/std_bus_energy_rates.csv
bussim2-0.3.3.dist-info/METADATA
bussim2-0.3.3.dist-info/WHEEL
bussim2-0.3.3.dist-info/licenses/LICENSE.txt
bussim2-0.3.3.dist-info/RECORD
