Metadata-Version: 2.1
Name: bussim2
Version: 0.3.3
Summary: Estimate energy, power and charging infrastructure needs for bus depots.
Project-URL: Documentation, https://gitlab.mtacp.info/Gideon.Weissman/bussim2/-/blob/main/README.md
Project-URL: Issues, https://gitlab.mtacp.info/Gideon.Weissman/bussim2/-/issues
Project-URL: Source, https://gitlab.mtacp.info/Gideon.Weissman/bussim2
Author-email: Gideon Weissman <gideon.weissman@nyct.com>, Joseph Sutton <joseph.sutton@nyct.com>, Elliot Ward <elliot.ward@nyct.com>
License-Expression: MIT
License-File: LICENSE.txt
Classifier: Development Status :: 4 - Beta
Classifier: Programming Language :: Python :: 3.7
Classifier: Programming Language :: Python :: 3.8
Classifier: Programming Language :: Python :: 3.9
Classifier: Programming Language :: Python :: 3.10
Classifier: Programming Language :: Python :: 3.11
Classifier: Programming Language :: Python :: Implementation :: CPython
Classifier: Programming Language :: Python :: Implementation :: PyPy
Requires-Python: >=3.7
Requires-Dist: airium>=0.2.4
Requires-Dist: jinja2>=3
Requires-Dist: matplotlib>=3.6
Requires-Dist: numpy>1
Requires-Dist: pandas>=1.5.0
Requires-Dist: requests>=2
Requires-Dist: simpy>=3
